hasy/__init__.py
hasy/_version.py
hasy/cli.py
hasy/create_hasy.py
hasy/hasy_tools.py
hasy-0.3.1.dist-info/METADATA
hasy-0.3.1.dist-info/WHEEL
hasy-0.3.1.dist-info/entry_points.txt
hasy-0.3.1.dist-info/top_level.txt
hasy-0.3.1.dist-info/RECORD
