Metadata-Version: 2.1
Name: hasy
Version: 0.3.1
Summary: Tools for the HASY dataset.
Home-page: https://github.com/MartinThoma/hasy
Author: Martin Thoma
Author-email: info@martin-thoma.de
Maintainer: Martin Thoma
Maintainer-email: info@martin-thoma.de
License: MIT
Download-URL: https://github.com/MartinThoma/hasy
Keywords: utility
Platform: Linux
Classifier: Development Status :: 3 - Alpha
Classifier: Environment :: Console
Classifier: Intended Audience :: Developers
Classifier: Intended Audience :: Information Technology
Classifier: License :: OSI Approved :: MIT License
Classifier: Natural Language :: English
Classifier: Operating System :: OS Independent
Classifier: Programming Language :: Python :: 3
Classifier: Programming Language :: Python :: 3 :: Only
Classifier: Programming Language :: Python :: 3.6
Classifier: Programming Language :: Python :: 3.7
Classifier: Programming Language :: Python :: 3.8
Classifier: Topic :: Software Development
Classifier: Topic :: Utilities
Requires-Python: >=3.6
Requires-Dist: click
Requires-Dist: imageio
Requires-Dist: scipy
Requires-Dist: numpy
Requires-Dist: pillow
Requires-Dist: six
Provides-Extra: all
Requires-Dist: tensorflow ; extra == 'all'
Requires-Dist: tflearn ; extra == 'all'
Requires-Dist: sklearn ; extra == 'all'
Requires-Dist: keras ; extra == 'all'
Requires-Dist: matplotlib ; extra == 'all'
